topicrankpy/__init__.py
topicrankpy/base.py
topicrankpy/data_structures.py
topicrankpy/extractinformation.py
topicrankpy/readers.py
topicrankpy/topicrank.py
topicrankpy/utils.py
topicrankpy-1.1.0.dist-info/LICENSE
topicrankpy-1.1.0.dist-info/METADATA
topicrankpy-1.1.0.dist-info/WHEEL
topicrankpy-1.1.0.dist-info/top_level.txt
topicrankpy-1.1.0.dist-info/RECORD
