Metadata-Version: 2.1
Name: topicrankpy
Version: 1.1.0
Summary: A Python package to get useful information from documents using TopicRank Algorithm.
Home-page: https://github.com/Aayushpatel007/topicrankpy
Author: Aayush Patel
Author-email: patelaayush678@gmail.com
License: MIT
Platform: UNKNOWN
Classifier: License :: OSI Approved :: MIT License
Classifier: Programming Language :: Python :: 3
Classifier: Programming Language :: Python :: 3.7
Requires-Dist: matplotlib (==3.1.1)
Requires-Dist: networkx (==2.4)
Requires-Dist: nltk (==3.4.5)
Requires-Dist: numpy (==1.17.2)
Requires-Dist: scikit-learn (==0.22)
Requires-Dist: scipy (==1.4.1)
Requires-Dist: six (==1.12.0)
Requires-Dist: spacy (==2.2.3)
Requires-Dist: textract (==1.6.3)
Requires-Dist: urlextract (==0.14.0)
